serve_me_once/__init__.py
serve_me_once-0.1.2.dist-info/LICENSE.md
serve_me_once-0.1.2.dist-info/WHEEL
serve_me_once-0.1.2.dist-info/METADATA
serve_me_once-0.1.2.dist-info/RECORD
