Metadata-Version: 2.1
Name: serve-me-once
Version: 0.1.2
Summary: 
Home-page: https://github.com/pbsds/serve-me-once/
Author: Peder Bergebakken Sundt
Author-email: pbsds@hotmail.com
Requires-Python: >=3.6
Classifier: Programming Language :: Python :: 3
Classifier: Programming Language :: Python :: 3.10
Classifier: Programming Language :: Python :: 3.6
Classifier: Programming Language :: Python :: 3.7
Classifier: Programming Language :: Python :: 3.8
Classifier: Programming Language :: Python :: 3.9
Project-URL: Repository, https://github.com/pbsds/serve-me-once/
